LICENSE.txt
MANIFEST.in
README.txt
setup.py
pcart_basic_theme/__init__.py
pcart_basic_theme/apps.py
pcart_basic_theme.egg-info/PKG-INFO
pcart_basic_theme.egg-info/SOURCES.txt
pcart_basic_theme.egg-info/dependency_links.txt
pcart_basic_theme.egg-info/not-zip-safe
pcart_basic_theme.egg-info/requires.txt
pcart_basic_theme.egg-info/top_level.txt
pcart_basic_theme/locale/ru/LC_MESSAGES/django.mo
pcart_basic_theme/locale/ru/LC_MESSAGES/django.po
pcart_basic_theme/locale/uk/LC_MESSAGES/django.mo
pcart_basic_theme/locale/uk/LC_MESSAGES/django.po
pcart_basic_theme/static/theme/css/style.css
pcart_basic_theme/static/vendor/bootstrap/css/bootstrap-theme.css
pcart_basic_theme/static/vendor/bootstrap/css/bootstrap-theme.css.map
pcart_basic_theme/static/vendor/bootstrap/css/bootstrap-theme.min.css
pcart_basic_theme/static/vendor/bootstrap/css/bootstrap-theme.min.css.map
pcart_basic_theme/static/vendor/bootstrap/css/bootstrap.css
pcart_basic_theme/static/vendor/bootstrap/css/bootstrap.css.map
pcart_basic_theme/static/vendor/bootstrap/css/bootstrap.min.css
pcart_basic_theme/static/vendor/bootstrap/css/bootstrap.min.css.map
pcart_basic_theme/static/vendor/bootstrap/fonts/glyphicons-halflings-regular.eot
pcart_basic_theme/static/vendor/bootstrap/fonts/glyphicons-halflings-regular.svg
pcart_basic_theme/static/vendor/bootstrap/fonts/glyphicons-halflings-regular.ttf
pcart_basic_theme/static/vendor/bootstrap/fonts/glyphicons-halflings-regular.woff
pcart_basic_theme/static/vendor/bootstrap/fonts/glyphicons-halflings-regular.woff2
pcart_basic_theme/static/vendor/bootstrap/js/bootstrap.js
pcart_basic_theme/static/vendor/bootstrap/js/bootstrap.min.js
pcart_basic_theme/static/vendor/bootstrap/js/npm.js
pcart_basic_theme/static/vendor/font-awesome/css/font-awesome.css
pcart_basic_theme/static/vendor/font-awesome/css/font-awesome.min.css
pcart_basic_theme/static/vendor/font-awesome/fonts/FontAwesome.otf
pcart_basic_theme/static/vendor/font-awesome/fonts/fontawesome-webfont.eot
pcart_basic_theme/static/vendor/font-awesome/fonts/fontawesome-webfont.svg
pcart_basic_theme/static/vendor/font-awesome/fonts/fontawesome-webfont.ttf
pcart_basic_theme/static/vendor/font-awesome/fonts/fontawesome-webfont.woff
